PySAM-stubs/AdjustmentFactors.pyi
PySAM-stubs/Annualoutput.pyi
PySAM-stubs/Battery.pyi
PySAM-stubs/BatteryStateful.pyi
PySAM-stubs/Battwatts.pyi
PySAM-stubs/Belpe.pyi
PySAM-stubs/Biomass.pyi
PySAM-stubs/Cashloan.pyi
PySAM-stubs/CbConstructionFinancing.pyi
PySAM-stubs/CbEmpiricalHceHeatLoss.pyi
PySAM-stubs/CbMsptSystemCosts.pyi
PySAM-stubs/Communitysolar.pyi
PySAM-stubs/DsgFluxPreprocess.pyi
PySAM-stubs/Equpartflip.pyi
PySAM-stubs/EtesElectricResistance.pyi
PySAM-stubs/Fuelcell.pyi
PySAM-stubs/GenericSystem.pyi
PySAM-stubs/Geothermal.pyi
PySAM-stubs/GeothermalCosts.pyi
PySAM-stubs/Grid.pyi
PySAM-stubs/Hcpv.pyi
PySAM-stubs/HostDeveloper.pyi
PySAM-stubs/Iec61853interp.pyi
PySAM-stubs/Iec61853par.pyi
PySAM-stubs/InvCecCg.pyi
PySAM-stubs/IphToLcoefcr.pyi
PySAM-stubs/Ippppa.pyi
PySAM-stubs/Irradproc.pyi
PySAM-stubs/IsccDesignPoint.pyi
PySAM-stubs/Layoutarea.pyi
PySAM-stubs/Lcoefcr.pyi
PySAM-stubs/Levpartflip.pyi
PySAM-stubs/LinearFresnelDsgIph.pyi
PySAM-stubs/Merchantplant.pyi
PySAM-stubs/MhkCosts.pyi
PySAM-stubs/MhkTidal.pyi
PySAM-stubs/MhkWave.pyi
PySAM-stubs/Poacalib.pyi
PySAM-stubs/Pv6parmod.pyi
PySAM-stubs/PvGetShadeLossMpp.pyi
PySAM-stubs/Pvsamv1.pyi
PySAM-stubs/Pvsandiainv.pyi
PySAM-stubs/Pvwattsv1.pyi
PySAM-stubs/Pvwattsv11ts.pyi
PySAM-stubs/Pvwattsv1Poa.pyi
PySAM-stubs/Pvwattsv5.pyi
PySAM-stubs/Pvwattsv51ts.pyi
PySAM-stubs/Pvwattsv7.pyi
PySAM-stubs/Pvwattsv8.pyi
PySAM-stubs/Saleleaseback.pyi
PySAM-stubs/Sco2AirCooler.pyi
PySAM-stubs/Sco2CompCurves.pyi
PySAM-stubs/Sco2CspSystem.pyi
PySAM-stubs/Sco2CspUdPcTables.pyi
PySAM-stubs/Singlediode.pyi
PySAM-stubs/Singlediodeparams.pyi
PySAM-stubs/Singleowner.pyi
PySAM-stubs/SixParsolve.pyi
PySAM-stubs/Snowmodel.pyi
PySAM-stubs/Solarpilot.pyi
PySAM-stubs/Swh.pyi
PySAM-stubs/TcsMSLF.pyi
PySAM-stubs/TcsgenericSolar.pyi
PySAM-stubs/TcslinearFresnel.pyi
PySAM-stubs/TcsmoltenSalt.pyi
PySAM-stubs/TcstroughEmpirical.pyi
PySAM-stubs/TcstroughPhysical.pyi
PySAM-stubs/TestUdPowerCycle.pyi
PySAM-stubs/Thermalrate.pyi
NREL_PySAM_stubs-3.0.0.dist-info/LICENSE
NREL_PySAM_stubs-3.0.0.dist-info/METADATA
NREL_PySAM_stubs-3.0.0.dist-info/WHEEL
NREL_PySAM_stubs-3.0.0.dist-info/top_level.txt
NREL_PySAM_stubs-3.0.0.dist-info/RECORD
