Metadata-Version: 2.1
Name: NREL-PySAM-stubs
Version: 3.0.0
Summary: National Renewable Energy Laboratory's System Advisor Model Python Wrapper, stub files
Home-page: http://www.github.com/nrel/pysam
Author: dguittet
Author-email: dguittet@nrel.gov
License: BSD 3-Clause
Platform: UNKNOWN
License-File: LICENSE
